{"expireTime":9007200843298323000,"key":"create-remote-file-node-https://cdn.dribbble.com/users/2538213/screenshots/7100529/carpooling_bh3.jpg","val":{"connection":"close","content-length":"399894","content-type":"image/jpeg","expires":"Sun, 28 Apr 2030 22:10:57 GMT","server":"Thumbor/6.7.0","etag":"\"2d752be416d38273ed9ad6be537a373ab35cc267\"","cache-control":"max-age=315576000,public","via":"1.1 varnish, 1.1 varnish","accept-ranges":"bytes","date":"Mon, 04 May 2020 01:55:32 GMT","age":"488675","x-served-by":"cache-lga21960-LGA, cache-ams21044-AMS","x-cache":"HIT, HIT","x-cache-hits":"1, 1","x-timer":"S1588557333.637156,VS0,VE2","vary":"Accept, Cookie"}}